{
    "last_gcn_results": {
        "Rush": {
            "precision": 0.6392405063291139,
            "recall": 0.8265139116202946,
            "f1-score": 0.7209136331192005,
            "support": 611.0
        },
        "Pass": {
            "precision": 0.7546296296296297,
            "recall": 0.5335515548281505,
            "f1-score": 0.6251198465963567,
            "support": 611.0
        },
        "accuracy": 0.6800327332242226,
        "macro avg": {
            "precision": 0.6969350679793718,
            "recall": 0.6800327332242226,
            "f1-score": 0.6730167398577787,
            "support": 1222.0
        },
        "weighted avg": {
            "precision": 0.6969350679793718,
            "recall": 0.6800327332242226,
            "f1-score": 0.6730167398577787,
            "support": 1222.0
        },
        "confusion_matrix": [
            [
                505,
                106
            ],
            [
                285,
                326
            ]
        ]
    },
    "best_gcn_results": {
        "Rush": {
            "precision": 0.6392405063291139,
            "recall": 0.8265139116202946,
            "f1-score": 0.7209136331192005,
            "support": 611.0
        },
        "Pass": {
            "precision": 0.7546296296296297,
            "recall": 0.5335515548281505,
            "f1-score": 0.6251198465963567,
            "support": 611.0
        },
        "accuracy": 0.6800327332242226,
        "macro avg": {
            "precision": 0.6969350679793718,
            "recall": 0.6800327332242226,
            "f1-score": 0.6730167398577787,
            "support": 1222.0
        },
        "weighted avg": {
            "precision": 0.6969350679793718,
            "recall": 0.6800327332242226,
            "f1-score": 0.6730167398577787,
            "support": 1222.0
        },
        "confusion_matrix": [
            [
                505,
                106
            ],
            [
                285,
                326
            ]
        ]
    },
    "rf_results": {
        "Rush": {
            "precision": 0.7085201793721974,
            "recall": 0.7757774140752864,
            "f1-score": 0.740625,
            "support": 611.0
        },
        "Pass": {
            "precision": 0.7522603978300181,
            "recall": 0.6808510638297872,
            "f1-score": 0.7147766323024055,
            "support": 611.0
        },
        "accuracy": 0.7283142389525368,
        "macro avg": {
            "precision": 0.7303902886011078,
            "recall": 0.7283142389525368,
            "f1-score": 0.7277008161512027,
            "support": 1222.0
        },
        "weighted avg": {
            "precision": 0.7303902886011077,
            "recall": 0.7283142389525368,
            "f1-score": 0.7277008161512027,
            "support": 1222.0
        },
        "confusion_matrix": [
            [
                474,
                137
            ],
            [
                195,
                416
            ]
        ]
    },
    "mlp_results": {
        "Rush": {
            "precision": 0.6884681583476764,
            "recall": 0.6546644844517185,
            "f1-score": 0.6711409395973155,
            "support": 611.0
        },
        "Pass": {
            "precision": 0.6708268330733229,
            "recall": 0.7037643207855974,
            "f1-score": 0.6869009584664537,
            "support": 611.0
        },
        "accuracy": 0.679214402618658,
        "macro avg": {
            "precision": 0.6796474957104996,
            "recall": 0.679214402618658,
            "f1-score": 0.6790209490318846,
            "support": 1222.0
        },
        "weighted avg": {
            "precision": 0.6796474957104996,
            "recall": 0.679214402618658,
            "f1-score": 0.6790209490318846,
            "support": 1222.0
        },
        "confusion_matrix": [
            [
                400,
                211
            ],
            [
                181,
                430
            ]
        ]
    },
    "config": {
        "RANDOM_SEED": 5,
        "GNN_EPOCHS": 500,
        "GNN_HIDDEN_CHANNELS": 64,
        "GNN_HIDDEN_LAYERS": 1,
        "GNN_LEARNING_RATE": 0.01,
        "GNN_DROPOUT": 0.4,
        "GNN_WEIGHT_DECAY": 5e-05,
        "RF_ESTIMATORS": 150,
        "MLP_HIDDEN_CHANNELS": 128,
        "MLP_HIDDEN_LAYERS": 3,
        "MLP_MAX_ITER": 3000,
        "MLP_LEARNING_RATE": 0.01,
        "MLP_ALPHA": 0.0005,
        "VALIDATION_SPLIT": 0.8,
        "TEST_SPLIT": 0.9,
        "SHOW_INFO": true
    }
}